odoo8_addon_base_url-8.0.0.1.0.99.dev8-py3.8-nspkg.pth
odoo_addons/base_url/README.rst
odoo_addons/base_url/__init__.py
odoo_addons/base_url/__openerp__.py
odoo_addons/base_url/models/__init__.py
odoo_addons/base_url/models/base_url.py
odoo_addons/base_url/security/ir.model.access.csv
odoo_addons/base_url/views/url_view.xml
odoo8_addon_base_url-8.0.0.1.0.99.dev8.dist-info/METADATA
odoo8_addon_base_url-8.0.0.1.0.99.dev8.dist-info/WHEEL
odoo8_addon_base_url-8.0.0.1.0.99.dev8.dist-info/namespace_packages.txt
odoo8_addon_base_url-8.0.0.1.0.99.dev8.dist-info/top_level.txt
odoo8_addon_base_url-8.0.0.1.0.99.dev8.dist-info/RECORD
